{
  "coord": {
    "lon": 1.2983,
    "lat": 52.6278
  },
  "weather": [
    {
      "id": 800,
      "main": "Clear",
      "description": "clear sky",
      "icon": "01d"
    }
  ],
  "base": "stations",
  "main": {
    "temp": 14.77,
    "feels_like": 14.13,
    "temp_min": 13.82,
    "temp_max": 15.55,
    "pressure": 1014,
    "humidity": 70,
    "sea_level": 1014,
    "grnd_level": 1010
  },
  "visibility": 10000,
  "wind": {
    "speed": 6.69,
    "deg": 200
  },
  "clouds": {
    "all": 0
  },
  "dt": 1773758297,
  "sys": {
    "type": 1,
    "id": 1467,
    "country": "GB",
    "sunrise": 1773727499,
    "sunset": 1773770490
  },
  "timezone": 0,
  "id": 2641181,
  "name": "Norwich",
  "cod": 200,
  "_last_updated_utc": "2026-03-17T14:42:48.511Z"
}